lsst/__init__.py
lsst/integration_test_reporting/__init__.py
lsst/integration_test_reporting/efd.py
lsst/integration_test_reporting/version.py
lsst/integration_test_reporting/bin/__init__.py
lsst/integration_test_reporting/bin/disabledreport.py
lsst/integration_test_reporting/bin/enabledreport.py
lsst/integration_test_reporting/bin/offlinereport.py
lsst/integration_test_reporting/bin/shutdownreport.py
lsst/integration_test_reporting/bin/standbyreport.py
lsst/integration_test_reporting/utils/__init__.py
lsst/integration_test_reporting/utils/constants.py
lsst/integration_test_reporting/utils/csc_cls.py
lsst/integration_test_reporting/utils/df.py
lsst/integration_test_reporting/utils/parser.py
integration_test_reporting-0.1.0.dist-info/LICENSE
integration_test_reporting-0.1.0.dist-info/METADATA
integration_test_reporting-0.1.0.dist-info/WHEEL
integration_test_reporting-0.1.0.dist-info/entry_points.txt
integration_test_reporting-0.1.0.dist-info/top_level.txt
integration_test_reporting-0.1.0.dist-info/zip-safe
integration_test_reporting-0.1.0.dist-info/RECORD
