Metadata-Version: 2.1
Name: integration-test-reporting
Version: 0.1.0
Summary: Reporting for LSST Control System Software Integration Testing
Home-page: https://github.com/lsst-sitcom/integration_test_reporting
Author: Michael Reuter
Author-email: mareuter@lsst.org
License: BSD 3-Clause License
Platform: UNKNOWN
Classifier: Intended Audience :: Science/Research
Classifier: License :: OSI Approved :: BSD License
Classifier: Operating System :: OS Independent
Classifier: Programming Language :: Python :: 3
Classifier: Programming Language :: Python :: 3.6
Classifier: Programming Language :: Python :: 3.7
Classifier: Topic :: Scientific/Engineering :: Astronomy
